visioncube/__init__.py
visioncube/alignment.py
visioncube/camera_calibration.py
visioncube/common.py
visioncube/docstring.py
visioncube/hdr.py
visioncube/light_segment.py
visioncube/match_template.py
visioncube/merge_mertens.py
visioncube/pipeline.py
visioncube/functional/__init__.py
visioncube/functional/arithmetic.py
visioncube/functional/basic.py
visioncube/functional/code_reader.py
visioncube/functional/color.py
visioncube/functional/contour.py
visioncube/functional/draw.py
visioncube/functional/filters.py
visioncube/functional/geometric.py
visioncube/functional/imageio.py
visioncube/functional/measure.py
visioncube/functional/misc.py
visioncube/functional/morphological.py
visioncube/functional/ocr.py
visioncube/functional/plotting.py
visioncube/functional/polar_unwrap.py
visioncube/functional/threshold.py
visioncube/functional_cuda/__init__.py
visioncube/functional_cuda/imageio.py
visioncube/functional_cuda/ocr.py
visioncube/functional_cuda/pcd_proc.py
visioncube/measure/__init__.py
visioncube/measure/color.py
visioncube/measure/distance.py
visioncube/operators/__init__.py
visioncube/operators/arithmetic.py
visioncube/operators/blur.py
visioncube/operators/code_reader.py
visioncube/operators/color.py
visioncube/operators/edge_detection.py
visioncube/operators/flip.py
visioncube/operators/geometric.py
visioncube/operators/morphological.py
visioncube/operators/polar_unwrap.py
visioncube/operators/sample.py
visioncube/operators/size.py
visioncube/operators/threshold.py
visioncube/operators_cuda/__init__.py
visioncube/operators_cuda/arithmetic.py
visioncube/operators_cuda/bbs.py
visioncube/operators_cuda/blur.py
visioncube/operators_cuda/color.py
visioncube/operators_cuda/edge_detection.py
visioncube/operators_cuda/flip.py
visioncube/operators_cuda/geometric.py
visioncube/operators_cuda/kmeans.py
visioncube/operators_cuda/morphological.py
visioncube/operators_cuda/sample.py
visioncube/operators_cuda/size.py
visioncube/recognition/__init__.py
visioncube-0.3.33.dist-info/METADATA
visioncube-0.3.33.dist-info/WHEEL
visioncube-0.3.33.dist-info/top_level.txt
visioncube-0.3.33.dist-info/RECORD
