Metadata-Version: 2.1
Name: visioncube
Version: 0.3.33
Summary: Image Processing Tool
Author: liying, luzzi, yanaenen, xi
Platform: any
Classifier: Programming Language :: Python :: 3
Requires-Dist: numpy
Requires-Dist: imgaug
Requires-Dist: opencv-python
Requires-Dist: opencv-contrib-python
Requires-Dist: torch
Requires-Dist: kornia
Requires-Dist: torchvision
Requires-Dist: PyYAML
Requires-Dist: matplotlib
Requires-Dist: shapely
Requires-Dist: pyzbar
Requires-Dist: pylibdmtx
